LICENSE
MANIFEST.in
NOTICE
README.md
requirements.txt
setup.cfg
setup.py
pyBetawi/__init__.py
pyBetawi/__main__.py
pyBetawi/assistant.py
pyBetawi/config.py
pyBetawi/decorator.py
pyBetawi/exceptions.py
pyBetawi/xd.py
pyBetawi/Clients/__init__.py
pyBetawi/Clients/client.py
pyBetawi/Clients/pytgcalls.py
pyBetawi/Clients/startup.py
pyBetawi/dB/__init__.py
pyBetawi/dB/_core.py
pyBetawi/dB/afk_db.py
pyBetawi/dB/antiflood_db.py
pyBetawi/dB/asst_fns.py
pyBetawi/dB/asstcmd_db.py
pyBetawi/dB/autoban_db.py
pyBetawi/dB/blacklist_chat_db.py
pyBetawi/dB/blacklist_db.py
pyBetawi/dB/botchat_db.py
pyBetawi/dB/broadcast_db.py
pyBetawi/dB/ch_db.py
pyBetawi/dB/dnd_db.py
pyBetawi/dB/echo_db.py
pyBetawi/dB/filestore_db.py
pyBetawi/dB/filter_db.py
pyBetawi/dB/forcesub_db.py
pyBetawi/dB/gban_mute_db.py
pyBetawi/dB/gcast_blacklist_db.py
pyBetawi/dB/greetings_db.py
pyBetawi/dB/logusers_db.py
pyBetawi/dB/mute_db.py
pyBetawi/dB/night_db.py
pyBetawi/dB/notes_db.py
pyBetawi/dB/nsfw_db.py
pyBetawi/dB/pmpermit_db.py
pyBetawi/dB/snips_db.py
pyBetawi/dB/vc_sudos.py
pyBetawi/dB/warn_db.py
pyBetawi/methods/Inlinebot.py
pyBetawi/methods/__init__.py
pyBetawi/methods/_database.py
pyBetawi/methods/_misc.py
pyBetawi/methods/changer.py
pyBetawi/methods/converter.py
pyBetawi/methods/func.py
pyBetawi/methods/funcb.py
pyBetawi/methods/helpers.py
pyBetawi/methods/hosting.py
pyBetawi/methods/queue.py
pyBetawi/methods/thumbnail.py
pyBetawi/pyrogram/__init__.py
pyBetawi/pyrogram/_wrappers.py
pyBetawi/pyrogram/func.py
pyBetawi/pyrogram/misc.py
pyBetawi/pyrogram/pastebin.py
pyBetawi/pyrogram/sections.py
pyBetawi/pyrogram/toolbot.py
pyBetawi/pyrogram/tools.py
pyBetawi/resources/__init__.py
pyBetawi/telethon/__init__.py
pyBetawi/telethon/dB/__init__.py
pyBetawi/telethon/dB/_core.py
pyBetawi/telethon/dB/afk_db.py
pyBetawi/telethon/dB/antiflood_db.py
pyBetawi/telethon/dB/asst_fns.py
pyBetawi/telethon/dB/asstcmd_db.py
pyBetawi/telethon/dB/autoban_db.py
pyBetawi/telethon/dB/blacklist_chat_db.py
py_Betawi.egg-info/PKG-INFO
py_Betawi.egg-info/SOURCES.txt
py_Betawi.egg-info/dependency_links.txt
py_Betawi.egg-info/requires.txt
py_Betawi.egg-info/top_level.txt